{"Fir": ["Fir_01_476", "Fir_19", "Fir_18", "Fir_17", "Fir_16", "Fir_15", "Fir_12", "Fir_11", "Fir_10", "Fir_139", "Fir_482", "Fir_226", "Fir_44", "Fir_45", "Fir_46", "Fir_47", "Fir_40", "Fir_41", "Fir_42", "Fir_43", "Fir_492", "Fir_223", "Fir_229", "Fir_183", "Fir_235", "Fir_232", "Fir_95", "Fir_93", "Fir_7", "Fir_6", "Fir_4", "Fir_3", "Fir_2", "Fir_9", "Fir_8", "Fir_146", "Fir_658", "Fir_26", "Fir_24", "Fir_25", "Fir_22", "Fir_23", "Fir_20", "Fir_21", "Fir_28", "Fir_29", "Fir_35", "Fir_34", "Fir_31", "Fir_30", "Fir_33", "Fir_32", "Fir_39"], "extractor": ["extractor_5", "extractor_213", "extractor_209", "extractor_83", "extractor_01_55", "extractor_46"], "Desktop": ["Desktop_02_255"], "BP": ["BP_Fan_2", "BP_Fan_633", "BP_Fan_238", "BP_Fan_01_206"], "Inner": ["Inner_Wall_Half_Door_96", "Inner_Door_Swing_888", "Inner_Wall_Half_Door_90", "Inner_Wall_Half_Door_142", "Inner_Door_Swing_01_C_29", "Inner_Door_Swing_01_C_28", "Inner_Door_Swing_01_C_27", "Inner_Door_Swing_01_C_23", "Inner_Door_Swing_01_C_22", "Inner_Wall_Half_Door_820", "Inner_Wall_8th_139", "Inner_Wall_Quart_Door_116", "Inner_Wall_Quart_Door_479", "Inner_Wall_Half_Arch_435", "Inner_Wall_Quart_93", "Inner_Wall_8th_136", "Inner_Door_Swing_01_C_0", "Inner_Wall_Close_Gap_83", "Inner_Wall_Quart_Door_160", "Inner_Wall_Half_Arch_01_24", "Inner_Door_Swing_725", "Inner_Wall_Quart_33", "Inner_Wall_Quart_Door_133", "Inner_Wall_Quart_Door_482", "Inner_Wall_Quart_Door_2", "Inner_Wall_Quart_Door_5", "Inner_Wall_Close_Gap_103", "Inner_Wall_Close_Gap_102", "Inner_Wall_Close_Gap_100", "Inner_Wall_Close_Gap_105", "Inner_Wall_Close_Gap_104", "Inner_Wall_Close_Gap_89", "Inner_Wall_Close_Gap_87", "Inner_Wall_Close_Gap_86", "Inner_Wall_Quart_119", "Inner_Wall_Half_Arch_148", "Inner_Door_Swing_01_C_25", "Inner_Door_Swing_01_C_24", "Inner_Door_Swing_01_C_26", "Inner_Wall_Half_Door_9", "Inner_Wall_Half_Door_6", "Inner_Wall_Half_Door_5", "Inner_Wall_Half_Door_3", "Inner_Wall_Half_Door_309", "Inner_Wall_Quart_plus_8th_4", "Inner_Wall_16th_142", "Inner_Wall_Close_Gap_137", "Inner_Wall_Close_Gap_134", "Inner_Wall_Close_Gap_130", "Inner_Wall_Close_Gap_139", "Inner_Wall_Close_Gap_32", "Inner_Wall_Quart_104", "Inner_Wall_Close_Gap_99", "Inner_Wall_Close_Gap_01_609", "Inner_Wall_Quart_94", "Inner_Wall_Close_Gap_129", "Inner_Wall_Half_Door_263", "Inner_Wall_Half_Door_103", "Inner_Wall_Half_Door_28", "Inner_Wall_Half_Door_01_21", "Inner_Wall_Half_Arch_168", "Inner_Wall_Quart_8", "Inner_Wall_Close_Gap_154", "Inner_Wall_Close_Gap_155", "Inner_Wall_Close_Gap_151", "Inner_Wall_Close_Gap_152", "Inner_Wall_Quart_120", "Inner_Wall_Half_Door_104", "Inner_Wall_Roof_5", "Inner_Wall_Quart_Door_203", "Inner_Wall_16th_01_209", "Inner_Wall_Close_Gap_200", "Inner_Wall_Quart_16", "Inner_Wall_Quart_Door_01_115", "Inner_Wall_Quart_01_144", "Inner_Wall_Half_Arch_203", "Inner_Wall_Close_Gap_145", "Inner_Wall_Quart_59", "Inner_Wall_Half_Door_113", "Inner_Wall_Quart_plus_8th_70", "Inner_Wall_Close_Gap_21", "Inner_Wall_Close_Gap_126", "Inner_Wall_Close_Gap_218", "Inner_Wall_Close_Gap_213", "Inner_Wall_Close_Gap_210", "Inner_Wall_Close_Gap_214", "Inner_Wall_Close_Gap_817", "Inner_Wall_Half_Arch_4", "Inner_Wall_Close_Gap_135", "Inner_Wall_Half_Arch_239", "Inner_Wall_Half_Arch_232", "Inner_Wall_Half_Arch_231", "Inner_Wall_Half_Arch_107", "Inner_Wall_Close_Gap_177", "Inner_Wall_Half_Door_122", "Inner_Wall_Close_Gap_90", "Inner_Wall_Close_Gap_36", "Inner_Wall_Close_Gap_38", "Inner_Wall_Close_Gap_198", "Inner_Wall_Half_Arch_102", "Inner_Wall_Close_Gap_351", "Inner_Wall_Quart_Arch_160", "Inner_Wall_Half_Door_19", "Inner_Wall_Half_Door_17", "Inner_Wall_Half_Door_11", "Inner_Wall_Close_Gap_160", "Inner_Wall_Close_Gap_257", "Inner_Wall_Close_Gap_254", "Inner_Door_Swing_01_C_41", "Inner_Door_Swing_01_C_40", "Inner_Wall_8th_01_163", "Inner_Wall_Close_Gap_233", "Inner_Wall_Close_Gap_235", "Inner_Wall_Close_Gap_239", "Inner_Wall_Quart_Arch_157", "Inner_Wall_Half_01_278", "Inner_Wall_Half_Door_24", "Inner_Wall_Half_Door_21", "Inner_Wall_Quart_Door_57", "Inner_Wall_Close_Gap_19", "Inner_Wall_Quart_Door_110", "Inner_Wall_Close_Gap_242", "Inner_Wall_Half_Door_39", "Inner_Wall_Half_Door_34", "Inner_Wall_Half_Door_36", "Inner_Wall_Quart_plus_8th_5", "Inner_Wall_Quart_plus_8th_6", "Inner_Wall_Close_Gap_147", "Inner_Wall_Quart_6", "Inner_Wall_Quart_7", "Inner_Wall_Quart_12", "Inner_Wall_Quart_10", "Inner_Wall_Quart_plus_8th_01_47", "Inner_Wall_Close_Gap_67", "Inner_Wall_Half_Door_27", "Inner_Wall_Half_Door_22", "Inner_Wall_Half_Door_23", "Inner_Wall_Half_Door_20", "Inner_Door_Swing_01_C_38", "Inner_Wall_Close_Gap_5", "Inner_Wall_Close_Gap_8", "Inner_Door_Swing_924", "Inner_Door_Swing_01_C_32", "Inner_Door_Swing_01_C_31", "Inner_Wall_Half_Door_149", "Inner_Wall_Close_Gap_101", "Inner_Door_Swing_01_C_39", "Inner_Wall_Quart_Arch_01_174", "Inner_Wall_Half_Door_186", "Inner_Wall_Half_Arch_151", "Inner_Wall_Half_Door_312", "Inner_Wall_Close_Gap_79", "Inner_Wall_Close_Gap_75", "Inner_Door_Swing_01_C_33", "Inner_Wall_Half_Arch_485", "Inner_Wall_Roof_01_156", "Inner_Wall_Close_Gap_263", "Inner_Wall_Close_Gap_260", "Inner_Wall_Close_Gap_266", "Inner_Door_Swing_1387", "Inner_Door_Swing_606", "Inner_Wall_Close_Gap_814", "Inner_Wall_Half_Door_53", "Inner_Wall_Half_Door_56", "Inner_Wall_Half_Arch_268", "Inner_Wall_Quart_Door_190", "Inner_Wall_Close_Gap_269", "Inner_Wall_Half_Door_199", "Inner_Wall_8th_Door_01_62", "Inner_Wall_Close_Gap_42", "Inner_Wall_Quart_157", "Inner_Wall_Half_Door_806", "Inner_Door_Swing_01_C_30", "Inner_Door_Swing_01_C_36", "Inner_Door_Swing_01_C_37", "Inner_Door_Swing_01_C_34", "Inner_Door_Swing_01_C_35", "Inner_Wall_Half_Door_234", "Inner_Wall_16th_123", "Inner_Wall_8th_2"], "Banister": ["Banister_Roof_Angle_01_47", "Banister_23", "Banister_26", "Banister_27", "Banister_25", "Banister_77", "Banister_194", "Banister_29", "Banister_01_602", "Banister_End_6", "Banister_81", "Banister_End_01_606", "Banister_234", "Banister_163", "Banister_314", "Banister_End_302", "Banister_End_263", "Banister_9", "Banister_8", "Banister_2", "Banister_7", "Banister_6", "Banister_4", "Banister_241", "Banister_298", "Banister_291", "Banister_19", "Banister_18", "Banister_12", "Banister_17", "Banister_16", "Banister_14", "Banister_288", "Banister_End_9", "Banister_End_13", "Banister_End_199", "Banister_31", "Banister_32"], "Shelf": ["Shelf_6", "Shelf_7", "Shelf_4", "Shelf_2", "Shelf_9", "Shelf_38", "Shelf_290", "Shelf_777", "Shelf_13", "Shelf_67", "Shelf_01_80", "Shelf_10", "Shelf_11"], "Lcd": ["Lcd_31", "Lcd_02_29", "Lcd_18"], "Sink": ["Sink_57", "Sink_184", "Sink_01_127", "Sink_123"], "8": ["8"], "Hedge": ["Hedge_559", "Hedge_555", "Hedge_554", "Hedge_556", "Hedge_551", "Hedge_550", "Hedge_552", "Hedge_399", "Hedge_398", "Hedge_393", "Hedge_392", "Hedge_390", "Hedge_397", "Hedge_396", "Hedge_395", "Hedge_394", "Hedge_496", "Hedge_19", "Hedge_18", "Hedge_15", "Hedge_14", "Hedge_17", "Hedge_16", "Hedge_11", "Hedge_10", "Hedge_12", "Hedge_492", "Hedge_498", "Hedge_499", "Hedge_252", "Hedge_338", "Hedge_629", "Hedge_253", "Hedge_628", "Hedge_627", "Hedge_251", "Hedge_626", "Hedge_87", "Hedge_255", "Hedge_609", "Hedge_608", "Hedge_274", "Hedge_601", "Hedge_600", "Hedge_603", "Hedge_258", "Hedge_607", "Hedge_606", "Hedge_275", "Hedge_133", "Hedge_179", "Hedge_178", "Hedge_177", "Hedge_176", "Hedge_174", "Hedge_173", "Hedge_172", "Hedge_171", "Hedge_170", "Hedge_549", "Hedge_546", "Hedge_540", "Hedge_541", "Hedge_389", "Hedge_384", "Hedge_385", "Hedge_386", "Hedge_380", "Hedge_381", "Hedge_382", "Hedge_536", "Hedge_13", "Hedge_534", "Hedge_768", "Hedge_769", "Hedge_619", "Hedge_612", "Hedge_613", "Hedge_610", "Hedge_611", "Hedge_616", "Hedge_169", "Hedge_222", "Hedge_220", "Hedge_227", "Hedge_162", "Hedge_163", "Hedge_164", "Hedge_166", "Hedge_167", "Hedge_346", "Hedge_347", "Hedge_472", "Hedge_476", "Hedge_262", "Hedge_573", "Hedge_572", "Hedge_571", "Hedge_570", "Hedge_577", "Hedge_576", "Hedge_575", "Hedge_574", "Hedge_579", "Hedge_578", "Hedge_371", "Hedge_370", "Hedge_373", "Hedge_372", "Hedge_375", "Hedge_374", "Hedge_377", "Hedge_376", "Hedge_379", "Hedge_378", "Hedge_01_154", "Hedge_285", "Hedge_284", "Hedge_287", "Hedge_286", "Hedge_282", "Hedge_289", "Hedge_288", "Hedge_30", "Hedge_755", "Hedge_599", "Hedge_598", "Hedge_591", "Hedge_590", "Hedge_593", "Hedge_592", "Hedge_595", "Hedge_594", "Hedge_597", "Hedge_354", "Hedge_624", "Hedge_623", "Hedge_622", "Hedge_621", "Hedge_537", "Hedge_351", "Hedge_544", "Hedge_350", "Hedge_602", "Hedge_531", "Hedge_539", "Hedge_538", "Hedge_115", "Hedge_114", "Hedge_117", "Hedge_116", "Hedge_111", "Hedge_110", "Hedge_113", "Hedge_112", "Hedge_119", "Hedge_118", "Hedge_250", "Hedge_564", "Hedge_358", "Hedge_566", "Hedge_560", "Hedge_561", "Hedge_563", "Hedge_568", "Hedge_257", "Hedge_362", "Hedge_360", "Hedge_361", "Hedge_366", "Hedge_364", "Hedge_365", "Hedge_368", "Hedge_254", "Hedge_296", "Hedge_297", "Hedge_294", "Hedge_295", "Hedge_298", "Hedge_299", "Hedge_409", "Hedge_408", "Hedge_740", "Hedge_403", "Hedge_588", "Hedge_589", "Hedge_582", "Hedge_583", "Hedge_580", "Hedge_586", "Hedge_584", "Hedge_585", "Hedge_259", "Hedge_618", "Hedge_631", "Hedge_635", "Hedge_638", "Hedge_596", "Hedge_03_135", "Hedge_107", "Hedge_104", "Hedge_105", "Hedge_102", "Hedge_103", "Hedge_101", "Hedge_108", "Hedge_811", "Hedge_209", "Hedge_208", "Hedge_461", "Hedge_205", "Hedge_703", "Hedge_357", "Hedge_355", "Hedge_206", "Hedge_353", "Hedge_352", "Hedge_654", "Hedge_359", "Hedge_200", "Hedge_203", "Hedge_419", "Hedge_367", "Hedge_369", "Hedge_824", "Hedge_828", "Hedge_139", "Hedge_138", "Hedge_132", "Hedge_131", "Hedge_130", "Hedge_137", "Hedge_136", "Hedge_135", "Hedge_134", "Hedge_292", "Hedge_293", "Hedge_839", "Hedge_348", "Hedge_349", "Hedge_341", "Hedge_342", "Hedge_343", "Hedge_344", "Hedge_345", "Hedge_175", "Hedge_754", "Hedge_657", "Hedge_402", "Hedge_653", "Hedge_650", "Hedge_651", "Hedge_313", "Hedge_312", "Hedge_310", "Hedge_831", "Hedge_314", "Hedge_319", "Hedge_318", "Hedge_406", "Hedge_420", "Hedge_428", "Hedge_128", "Hedge_129", "Hedge_124", "Hedge_126", "Hedge_127", "Hedge_120", "Hedge_121", "Hedge_122", "Hedge_123", "Hedge_655", "Hedge_391", "Hedge_106", "Hedge_339", "Hedge_335", "Hedge_334", "Hedge_337", "Hedge_336", "Hedge_332", "Hedge_387", "Hedge_482", "Hedge_481", "Hedge_480", "Hedge_487", "Hedge_485", "Hedge_484", "Hedge_489", "Hedge_241", "Hedge_240", "Hedge_243", "Hedge_245", "Hedge_244", "Hedge_247", "Hedge_249", "Hedge_02_202", "Hedge_548", "Hedge_383", "Hedge_632", "Hedge_543", "Hedge_267", "Hedge_266", "Hedge_637", "Hedge_265", "Hedge_388", "Hedge_639", "Hedge_668", "Hedge_261", "Hedge_661", "Hedge_260", "Hedge_666", "Hedge_665", "Hedge_664", "Hedge_469", "Hedge_468", "Hedge_460", "Hedge_463", "Hedge_462", "Hedge_125", "Hedge_658", "Hedge_168", "Hedge_84", "Hedge_646", "Hedge_77", "Hedge_645", "Hedge_644", "Hedge_647", "Hedge_326", "Hedge_327", "Hedge_322", "Hedge_323", "Hedge_495", "Hedge_82", "Hedge_83", "Hedge_80", "Hedge_81", "Hedge_256", "Hedge_85", "Hedge_88", "Hedge_89", "Hedge_68", "Hedge_69", "Hedge_60", "Hedge_61", "Hedge_62", "Hedge_63", "Hedge_64", "Hedge_65", "Hedge_66", "Hedge_67", "Hedge_153", "Hedge_152", "Hedge_155", "Hedge_154", "Hedge_157", "Hedge_156", "Hedge_271", "Hedge_478", "Hedge_479", "Hedge_473", "Hedge_475", "Hedge_643", "Hedge_648", "Hedge_567", "Hedge_642", "Hedge_199", "Hedge_331", "Hedge_330", "Hedge_444", "Hedge_316", "Hedge_633", "Hedge_634", "Hedge_95", "Hedge_94", "Hedge_97", "Hedge_264", "Hedge_263", "Hedge_90", "Hedge_93", "Hedge_92", "Hedge_99", "Hedge_98", "Hedge_269", "Hedge_268", "Hedge_79", "Hedge_78", "Hedge_73", "Hedge_72", "Hedge_70", "Hedge_76", "Hedge_75", "Hedge_74", "Hedge_291", "Hedge_483", "Hedge_449", "Hedge_448", "Hedge_447", "Hedge_446", "Hedge_445", "Hedge_443", "Hedge_442", "Hedge_441", "Hedge_440", "Hedge_520", "Hedge_248", "Hedge_488", "Hedge_242", "Hedge_617", "Hedge_614", "Hedge_615", "Hedge_221", "Hedge_290", "Hedge_497", "Hedge_490", "Hedge_109", "Hedge_493", "Hedge_304", "Hedge_308", "Hedge_309", "Hedge_278", "Hedge_279", "Hedge_270", "Hedge_277", "Hedge_565", "Hedge_48", "Hedge_49", "Hedge_46", "Hedge_47", "Hedge_44", "Hedge_45", "Hedge_42", "Hedge_43", "Hedge_40", "Hedge_41", "Hedge_418", "Hedge_417", "Hedge_694", "Hedge_471", "Hedge_452", "Hedge_453", "Hedge_454", "Hedge_456", "Hedge_457", "Hedge_459", "Hedge_158", "Hedge_562", "Hedge_213", "Hedge_630", "Hedge_620", "Hedge_569", "Hedge_669", "Hedge_604", "Hedge_486", "Hedge_216", "Hedge_214", "Hedge_210", "Hedge_356", "Hedge_204", "Hedge_207", "Hedge_201", "Hedge_202", "Hedge_464", "Hedge_467", "Hedge_466", "Hedge_51", "Hedge_50", "Hedge_53", "Hedge_52", "Hedge_55", "Hedge_57", "Hedge_56", "Hedge_59", "Hedge_58", "Hedge_159", "Hedge_511", "Hedge_510", "Hedge_512", "Hedge_515", "Hedge_514", "Hedge_517", "Hedge_516", "Hedge_519", "Hedge_518", "Hedge_425", "Hedge_424", "Hedge_427", "Hedge_426", "Hedge_421", "Hedge_423", "Hedge_422", "Hedge_491", "Hedge_429", "Hedge_302", "Hedge_303", "Hedge_845", "Hedge_848", "Hedge_502", "Hedge_198", "Hedge_195", "Hedge_194", "Hedge_197", "Hedge_196", "Hedge_191", "Hedge_190", "Hedge_193", "Hedge_192", "Hedge_160", "Hedge_161", "Hedge_218", "Hedge_219", "Hedge_217", "Hedge_215", "Hedge_24", "Hedge_25", "Hedge_26", "Hedge_27", "Hedge_20", "Hedge_21", "Hedge_23", "Hedge_28", "Hedge_29", "Hedge_503", "Hedge_500", "Hedge_501", "Hedge_506", "Hedge_507", "Hedge_504", "Hedge_508", "Hedge_229", "Hedge_228", "Hedge_436", "Hedge_437", "Hedge_311", "Hedge_435", "Hedge_432", "Hedge_433", "Hedge_431", "Hedge_438", "Hedge_439", "Hedge_305", "Hedge_306", "Hedge_317", "Hedge_307", "Hedge_300", "Hedge_301", "Hedge_315", "Hedge_434", "Hedge_430", "Hedge_470", "Hedge_188", "Hedge_189", "Hedge_186", "Hedge_187", "Hedge_184", "Hedge_185", "Hedge_182", "Hedge_183", "Hedge_180", "Hedge_181", "Hedge_605", "Hedge_477", "Hedge_545", "Hedge_474", "Hedge_281", "Hedge_542", "Hedge_223", "Hedge_226", "Hedge_225", "Hedge_224", "Hedge_37", "Hedge_36", "Hedge_35", "Hedge_34", "Hedge_33", "Hedge_32", "Hedge_31", "Hedge_39", "Hedge_38", "Hedge_272", "Hedge_535", "Hedge_273", "Hedge_533", "Hedge_532", "Hedge_530", "Hedge_276", "Hedge_641", "Hedge_401", "Hedge_400", "Hedge_407", "Hedge_405", "Hedge_404", "Hedge_547", "Hedge_211", "Hedge_558", "Hedge_329", "Hedge_465", "Hedge_324", "Hedge_557", "Hedge_151", "Hedge_150", "Hedge_553", "Hedge_234", "Hedge_235", "Hedge_236", "Hedge_237", "Hedge_230", "Hedge_231", "Hedge_232", "Hedge_233", "Hedge_238", "Hedge_239", "Hedge_280", "Hedge_283", "Hedge_528", "Hedge_529", "Hedge_521", "Hedge_522", "Hedge_523", "Hedge_524", "Hedge_525", "Hedge_526", "Hedge_527", "Hedge_140", "Hedge_414", "Hedge_415", "Hedge_416", "Hedge_410", "Hedge_411", "Hedge_412", "Hedge_413", "Hedge_54", "Hedge_587", "Hedge_700", "Hedge_701", "Hedge_3", "Hedge_2", "Hedge_5", "Hedge_4", "Hedge_7", "Hedge_9", "Hedge_8", "Hedge_753", "Hedge_328", "Hedge_450", "Hedge_325", "Hedge_451", "Hedge_320", "Hedge_321", "Hedge_455", "Hedge_494", "Hedge_148", "Hedge_149", "Hedge_142", "Hedge_143", "Hedge_141", "Hedge_146", "Hedge_147", "Hedge_144", "Hedge_145", "Hedge_333"], "Pool": ["Pool_Table_01_109", "Pool_Table_77", "Pool_Table_7"], "bin": ["bin_13", "bin_01_5", "bin_02_7", "bin_22", "bin_28", "bin_25", "bin_35", "bin_38"], "coffee": ["coffee_table_243", "coffee_table_01_48", "coffee_table_02_106"], "Car": ["Car_37", "Car_34", "Car_7", "Car_4", "Car_69", "Car_36", "Car_25", "Car_27", "Car_21", "Car_20", "Car_129", "Car_127", "Car_10", "Car_11", "Car_12", "Car_14", "Car_17", "Car_18", "Car_26", "Car_44", "Car_117", "Car_63", "Car_64", "Car_35", "Car_32", "Car_Porch_Prefab_2399", "Car_42", "Car_Porch_Prefab_01_479", "Car_97", "Car_47", "Car_Porch_01", "Car_142", "Car_54", "Car_58", "Car_92", "Car_Porch_Prefab_6482", "Car_30", "Car_29", "Car_28", "Car_43", "Car_33", "Car_139", "Car_132", "Car_135", "Car_55", "Car_56", "Car_57", "Car_52", "Car_53", "Car_59", "Car_38", "Car_107", "Car_100", "Car_103", "Car_39", "Car_Porch_Prefab_4184", "Car_41", "Car_40", "Car_46", "Car_45", "Car_49", "Car_48", "Car_112", "Car_50", "Car_51", "Car_Porch_Prefab_6", "Car_77", "Car_74", "Car_87", "Car_81", "Car_80", "Car_Porch_Prefab_8258", "Car_60", "Car_62", "Car_65", "Car_01_32", "Car_66", "Car_Porch_Prefab_10575"], "Leaves": ["Leaves_3", "Leaves_2", "Leaves_4", "Leaves_6", "Leaves_01_360", "Leaves_366"], "Headphones": ["Headphones_01_60", "Headphones_28", "Headphones_37", "Headphones_267"], "Skateboard": ["Skateboard_712", "Skateboard_01_16", "Skateboard_64"], "CameraActor": ["CameraActor_0", "CameraActor_1"], "fan": ["fan_39", "fan_4", "fan_93", "fan_206"], "2": ["2"], "Swimming": ["Swimming_Pool_Curve_10", "Swimming_Pool_Steps_188", "Swimming_Pool_Edge_643", "Swimming_Pool_Edge_642", "Swimming_Pool_Steps_194", "Swimming_Pool_Curve_8", "Swimming_Pool_Curve_9", "Swimming_Pool_Curve_2", "Swimming_Pool_Curve_3", "Swimming_Pool_Curve_4", "Swimming_Pool_Curve_5", "Swimming_Pool_Curve_6", "Swimming_Pool_Steps_96", "Swimming_Pool_Steps_87", "Swimming_Pool_Steps_01_185", "Swimming_Pool_Edge_01_228", "Swimming_Pool_Steps_5", "Swimming_Pool_Edge_47", "Swimming_Pool_Edge_45", "Swimming_Pool_Edge_42", "Swimming_Pool_Edge_43", "Swimming_Pool_Edge_41", "Swimming_Pool_Edge_46", "Swimming_Pool_Edge_44", "Swimming_Pool_Edge_3", "Swimming_Pool_Edge_5", "Swimming_Pool_Edge_7", "Swimming_Pool_Edge_6", "Swimming_Pool_Edge_48", "Swimming_Pool_Edge_8", "Swimming_Pool_Floor_93", "Swimming_Pool_Edge_61", "Swimming_Pool_Edge_19", "Swimming_Pool_Edge_11", "Swimming_Pool_Edge_10", "Swimming_Pool_Edge_13", "Swimming_Pool_Edge_12", "Swimming_Pool_Edge_15", "Swimming_Pool_Edge_14", "Swimming_Pool_Edge_16", "Swimming_Pool_Edge_2", "Swimming_Pool_Edge_4", "Swimming_Pool_Edge_35", "Swimming_Pool_Edge_37", "Swimming_Pool_Edge_33", "Swimming_Pool_Edge_32", "Swimming_Pool_Edge_30", "Swimming_Pool_Edge_39", "Swimming_Pool_Steps_02_191", "Swimming_Pool_Edge_20", "Swimming_Pool_Edge_21", "Swimming_Pool_Edge_22", "Swimming_Pool_Edge_23", "Swimming_Pool_Edge_24", "Swimming_Pool_Edge_26", "Swimming_Pool_Edge_27", "Swimming_Pool_Edge_29", "Swimming_Pool_Floor_4", "Swimming_Pool_Edge_622", "Swimming_Pool_Curve_01_234", "Swimming_Pool_Floor_01_251", "Swimming_Pool_Curve_618"], "Office": ["Office_Desk_01_246"], "sofa": ["sofa_long_01_99", "sofa_long_2", "sofa_long_3"], "Laptop": ["Laptop_01_51"], "258": ["258"], "Oven": ["Oven_152", "Oven_01_66", "Oven_212", "Oven_195"], "Keyboard": ["Keyboard_01_261"], "small": ["small_table_03_87", "small_table_58", "small_table_738", "small_table_6", "small_table_01_55", "small_table_14", "small_table_02_24"], "Mouse": ["Mouse_01_271"], "Tablet": ["Tablet_01_31"], "Mug": ["Mug_14", "Mug_195", "Mug_19", "Mug_11", "Mug_10", "Mug_13", "Mug_12", "Mug_01_109", "Mug_20", "Mug_169", "Mug_166", "Mug_37", "Mug_34", "Mug_709", "Mug_3", "Mug_2", "Mug_5", "Mug_4", "Mug_6", "Mug_93", "Mug_96", "Mug_163"], "driveway": ["driveway_16th_Curve_432", "driveway_16th_Curve_356", "driveway_16th_Curve_383", "driveway_16th_Curve_5", "driveway_16th_Curve_4", "driveway_16th_Curve_6", "driveway_16th_Curve_3", "driveway_16th_Curve_371", "driveway_16th_Curve_396", "driveway_16th_Curve_368", "driveway_16th_Curve_02_254", "driveway_16th_Curve_11", "driveway_16th_Curve_19", "driveway_16th_Curve_18", "driveway_16th_Curve_186", "driveway_16th_Curve_20", "driveway_16th_Curve_21", "driveway_16th_Curve_25", "driveway_16th_Curve_26", "driveway_16th_Curve_27", "driveway_16th_Curve_198", "driveway_16th_Curve_38", "driveway_16th_Curve_37", "driveway_16th_Curve_34", "driveway_16th_Curve_30", "driveway_16th_Curve_189", "driveway_16th_Curve_51", "driveway_16th_Curve_01_261", "driveway_16th_Curve_85", "driveway_16th_Curve_419", "driveway_16th_Curve_230", "driveway_16th_Curve_422"], "table": ["table_01_115"], "Picture": ["Picture_Frame_104", "Picture_Frame_78", "Picture_Frame_100", "Picture_Frame_107", "Picture_Frame_74", "Picture_Frame_7", "Picture_Frame_4", "Picture_Frame_5", "Picture_Frame_3", "Picture_Frame_8", "Picture_Frame_17", "Picture_Frame_01_4", "Picture_Frame_767", "Picture_Frame_715", "Picture_Frame_11", "Picture_Frame_13", "Picture_Frame_14", "Picture_Frame_771"], "Medium": ["Medium_House_Prefab_01_23176", "Medium_House_Prefab_49874", "Medium_House_Prefab_40975", "Medium_House_Prefab_80664", "Medium_House_Prefab_95387", "Medium_House_Prefab_63253"], "Staircase": ["Staircase_02_27", "Staircase_284", "Staircase_35", "Staircase_Extra_Banister_01_233", "Staircase_Extra_Banister_68", "Staircase_305", "Staircase_01_228", "Staircase_Extra_Banister_65", "Staircase_154", "Staircase_3", "Staircase_74"], "3": ["3"], "7": ["7"], "Light": ["Light_Switch_8", "Light_Switch_2", "Light_Switch_5", "Light_Switch_6", "Light_Switch_10", "Light_Switch_01_61", "Light_Switch_763", "Light_Switch_68", "Light_Switch_67", "Light_Switch_65"], "Stairs": ["Stairs_Beam_Quart_166", "Stairs_Beam_Quart_163", "Stairs_Beam_Quart_55", "Stairs_Prefab_688", "Stairs_Beam_Quart_14", "Stairs_Prefab_01_1918", "Stairs_Prefab_471", "Stairs_Beam_Quart_819", "Stairs_Prefab_149", "Stairs_Beam_Quart_01_50", "Stairs_Beam_Quart_100", "Stairs_Prefab_1341", "Stairs_Beam_Quart_8", "Stairs_Beam_Quart_9", "Stairs_Beam_Quart_2", "Stairs_Beam_Quart_4", "Stairs_Beam_Quart_5", "Stairs_Beam_Quart_51", "Stairs_Prefab_429", "Stairs_Beam_Quart_72"], "Kitchen": ["Kitchen_Splash_Tile_01_31", "Kitchen_Splash_Tile_5", "Kitchen_Splash_Tile_4", "Kitchen_Splash_Tile_7", "Kitchen_Splash_Tile_6", "Kitchen_Splash_Tile_2", "Kitchen_Splash_Tile_9", "Kitchen_Splash_Tile_198", "Kitchen_Unit_173", "Kitchen_Cupboard_4", "Kitchen_Cupboard_6", "Kitchen_Cupboard_7", "Kitchen_Cupboard_3", "Kitchen_Cupboard_9", "Kitchen_Unit_Sink_01_15", "Kitchen_Unit_Sink_187", "Kitchen_Cupboard_Fan_149", "Kitchen_Unit_155", "Kitchen_Cupboard_185", "Kitchen_Cupboard_Fan_189", "Kitchen_Cupboard_159", "Kitchen_Unit_Sink_136", "Kitchen_Unit_Sink_53", "Kitchen_Unit_6", "Kitchen_Unit_4", "Kitchen_Unit_8", "Kitchen_Unit_7", "Kitchen_Unit_192", "Kitchen_Unit_190", "Kitchen_Splash_Tile_11", "Kitchen_Splash_Tile_10", "Kitchen_Splash_Tile_13", "Kitchen_Splash_Tile_12", "Kitchen_Cupboard_142", "Kitchen_Cupboard_72", "Kitchen_Unit_14", "Kitchen_Unit_16", "Kitchen_Unit_17", "Kitchen_Unit_10", "Kitchen_Unit_12", "Kitchen_Unit_13", "Kitchen_Unit_18", "Kitchen_Splash_Tile_15", "Kitchen_Unit_27", "Kitchen_Splash_Tile_36", "Kitchen_Cupboard_146", "Kitchen_Splash_Tile_215", "Kitchen_Unit_Corner_01_180", "Kitchen_Cupboard_02_22", "Kitchen_Unit_21", "Kitchen_Cupboard_Fan_01_196", "Kitchen_Unit_02_11", "Kitchen_Unit_56", "Kitchen_Unit_2", "Kitchen_Unit_3", "Kitchen_Cupboard_Fan_209", "Kitchen_Cupboard_14", "Kitchen_Cupboard_12", "Kitchen_Cupboard_Fan_100", "Kitchen_Unit_182", "Kitchen_Unit_01_132"], "Sofa": ["Sofa_52", "Sofa_87", "Sofa_01_742", "Sofa_4", "Sofa_02_49", "Sofa_10", "Sofa_121", "Sofa_112"], "Tree": ["Tree_13", "Tree_11", "Tree_10", "Tree_16", "Tree_886", "Tree_858", "Tree_855", "Tree_871", "Tree_874", "Tree_868", "Tree_23", "Tree_20", "Tree_26", "Tree_24", "Tree_25", "Tree_28", "Tree_893", "Tree_890", "Tree_878", "Tree_884", "Tree_861", "Tree_881", "Tree_851", "Tree_01_7", "Tree_865", "Tree_159", "Tree_5", "Tree_9"], "Garage": ["Garage_Door_BP3_966", "Garage_Door_Half_BP12_424", "Garage_Door_Half_BP13_374", "Garage_Door_BP2_590", "Garage_Door_BP2_C_1", "Garage_Door_Half_BP_C_13", "Garage_Door_Half_BP_C_12", "Garage_Door_Half_BP_C_11", "Garage_Door_Half_BP_C_17", "Garage_Door_Half_BP_C_16", "Garage_Door_Half_BP_C_15", "Garage_Door_Half_BP_C_14", "Garage_Door_Half_BP_C_19", "Garage_Door_Half_BP_C_18", "Garage_Door_Half_BP_C_20", "Garage_Door_Half_BP_C_21"], "Rock": ["Rock_26", "Rock_4", "Rock_5", "Rock_6", "Rock_7", "Rock_146", "Rock_18", "Rock_2", "Rock_3", "Rock_20", "Rock_01_43", "Rock_24", "Rock_21", "Rock_229", "Rock_75", "Rock_220", "Rock_17", "Rock_14", "Rock_15", "Rock_10", "Rock_11", "Rock_57", "Rock_8", "Rock_9", "Rock_68", "Rock_22"], "Toilet": ["Toilet_54", "Toilet_01_124", "Toilet_126", "Toilet_181"], "Gamepad": ["Gamepad_2", "Gamepad_01_63", "Gamepad_264"], "Veranda": ["Veranda_01_137", "Veranda_421", "Veranda_140", "Veranda_143", "Veranda_174", "Veranda_4", "Veranda_493", "Veranda_201", "Veranda_Banister_5", "Veranda_Banister_4", "Veranda_Banister_6", "Veranda_Banister_3"], "Driveway": ["Driveway_350", "Driveway_8th_30", "Driveway_01_306", "Driveway_98", "Driveway_99", "Driveway_Edge_89", "Driveway_97", "Driveway_8th_388", "Driveway_58", "Driveway_8th_21", "Driveway_125", "Driveway_103", "Driveway_Half_10", "Driveway_Half_13", "Driveway_Half_15", "Driveway_Half_14", "Driveway_Half_17", "Driveway_Half_16", "Driveway_Half_19", "Driveway_8th_150", "Driveway_8th_01_293", "Driveway_16th_2", "Driveway_16th_5", "Driveway_Half_61", "Driveway_4", "Driveway_167", "Driveway_164", "Driveway_Edge_575", "Driveway_217", "Driveway_109", "Driveway_105", "Driveway_104", "Driveway_107", "Driveway_101", "Driveway_100", "Driveway_10", "Driveway_11", "Driveway_12", "Driveway_14", "Driveway_15", "Driveway_16", "Driveway_17", "Driveway_18", "Driveway_19", "Driveway_404", "Driveway_163", "Driveway_8th_374", "Driveway_Quart_2", "Driveway_8th_192", "Driveway_25", "Driveway_24", "Driveway_27", "Driveway_26", "Driveway_21", "Driveway_22", "Driveway_29", "Driveway_28", "Driveway_393", "Driveway_Edge_24", "Driveway_Edge_25", "Driveway_Edge_20", "Driveway_Edge_21", "Driveway_Edge_22", "Driveway_Edge_23", "Driveway_Half_43", "Driveway_96", "Driveway_8th_17", "Driveway_8th_16", "Driveway_8th_15", "Driveway_8th_14", "Driveway_8th_13", "Driveway_8th_12", "Driveway_8th_11", "Driveway_8th_10", "Driveway_8th_19", "Driveway_8th_18", "Driveway_162", "Driveway_Half_29", "Driveway_38", "Driveway_39", "Driveway_32", "Driveway_33", "Driveway_30", "Driveway_36", "Driveway_37", "Driveway_35", "Driveway_Half_21", "Driveway_389", "Driveway_Half_12", "Driveway_Half_141", "Driveway_Half_01_281", "Driveway_49", "Driveway_48", "Driveway_47", "Driveway_45", "Driveway_43", "Driveway_42", "Driveway_41", "Driveway_31", "Driveway_8th_7", "Driveway_8th_6", "Driveway_8th_5", "Driveway_8th_9", "Driveway_8th_8", "Driveway_Half_319", "Driveway_60", "Driveway_16th_8", "Driveway_8th_31", "Driveway_8th_33", "Driveway_8th_32", "Driveway_8th_35", "Driveway_8th_36", "Driveway_8th_39", "Driveway_59", "Driveway_54", "Driveway_55", "Driveway_57", "Driveway_50", "Driveway_51", "Driveway_52", "Driveway_53", "Driveway_16th_380", "Driveway_6", "Driveway_7", "Driveway_5", "Driveway_8", "Driveway_Edge_15", "Driveway_Edge_14", "Driveway_Edge_17", "Driveway_Edge_16", "Driveway_Edge_11", "Driveway_Edge_13", "Driveway_Edge_12", "Driveway_Edge_19", "Driveway_Edge_18", "Driveway_Edge_01_281", "Driveway_8th_28", "Driveway_8th_29", "Driveway_8th_26", "Driveway_8th_27", "Driveway_8th_24", "Driveway_8th_25", "Driveway_8th_23", "Driveway_8th_20", "Driveway_61", "Driveway_63", "Driveway_62", "Driveway_65", "Driveway_64", "Driveway_67", "Driveway_66", "Driveway_69", "Driveway_68", "Driveway_102", "Driveway_89", "Driveway_88", "Driveway_83", "Driveway_82", "Driveway_81", "Driveway_80", "Driveway_87", "Driveway_86", "Driveway_85", "Driveway_84", "Driveway_8th_295", "Driveway_8th_297", "Driveway_8th_50", "Driveway_44", "Driveway_76", "Driveway_77", "Driveway_74", "Driveway_72", "Driveway_73", "Driveway_71", "Driveway_78", "Driveway_509", "Driveway_502", "Driveway_90", "Driveway_91", "Driveway_92", "Driveway_93", "Driveway_94", "Driveway_95", "Driveway_112", "Driveway_111", "Driveway_8th_40", "Driveway_8th_42", "Driveway_8th_43", "Driveway_8th_45", "Driveway_8th_46", "Driveway_316", "Driveway_Half_353", "Driveway_8th_77", "Driveway_Quart_01_273", "Driveway_Half_30", "Driveway_Half_34", "Driveway_16th_43", "Driveway_20", "Driveway_Half_431", "Driveway_16th_429", "Driveway_113", "Driveway_Half_28", "Driveway_Half_22", "Driveway_Half_23", "Driveway_Half_24", "Driveway_Half_25", "Driveway_Half_26", "Driveway_Half_27", "Driveway_Half_4", "Driveway_Half_3", "Driveway_Half_2", "Driveway_Half_416", "Driveway_79", "Driveway_8th_436", "Driveway_165", "Driveway_16th_82", "Driveway_117", "Driveway_114", "Driveway_Edge_9", "Driveway_Edge_8", "Driveway_Edge_3", "Driveway_Edge_2", "Driveway_Edge_5", "Driveway_Edge_4", "Driveway_Edge_6", "Driveway_16th_01_277", "Driveway_8th_425"], "Chair": ["Chair_118", "Chair_781", "Chair_784", "Chair_8", "Chair_5", "Chair_4", "Chair_6", "Chair_240", "Chair_03_224"], "Landscape": ["Landscape_0"], "Drinks": ["Drinks_Can_84", "Drinks_Can_85", "Drinks_Can_87", "Drinks_Can_80", "Drinks_Can_81", "Drinks_Can_181", "Drinks_Can_178", "Drinks_Can_175", "Drinks_Can_172", "Drinks_Can_718", "Drinks_Can_793", "Drinks_Can_796", "Drinks_Can_799", "Drinks_Can_03_45", "Drinks_Can_11", "Drinks_Can_31", "Drinks_Can_33", "Drinks_Can_802", "Drinks_Can_05_68", "Drinks_Can_04_71", "Drinks_Can_13", "Drinks_Can_10", "Drinks_Can_14", "Drinks_Can_745", "Drinks_Can_8", "Drinks_Can_75", "Drinks_Can_74", "Drinks_Can_77", "Drinks_Can_78", "Drinks_Can_01_51", "Drinks_Can_9", "Drinks_Can_7", "Drinks_Can_62", "Drinks_Can_06_57", "Drinks_Can_748", "Drinks_Can_304", "Drinks_Can_58", "Drinks_Can_55", "Drinks_Can_54", "Drinks_Can_51", "Drinks_Can_07_65", "Drinks_Can_48", "Drinks_Can_42", "Drinks_Can_32", "Drinks_Can_754", "Drinks_Can_751", "Drinks_Can_790", "Drinks_Can_90"], "Outer": ["Outer_Wall_Half_Win_01_8", "Outer_Wall_Quart_Garage_260", "Outer_Wall_Quart_163", "Outer_Wall_Half_Win_446", "Outer_Wall_Half_Garage_82", "Outer_Wall_Quart_Win_136", "Outer_Wall_Half_Door_145", "Outer_Door_BP_C_5", "Outer_Door_BP_C_4", "Outer_Door_BP_C_3", "Outer_Wall_Quart_Win_316", "Outer_Door_Swing_7084", "Outer_Wall_Quart_Roof_7", "Outer_Wall_Quart_Roof_6", "Outer_Wall_Quart_Roof_5", "Outer_Wall_Quart_Roof_4", "Outer_Wall_Quart_Roof_3", "Outer_Door_Swing_7510", "Outer_Door_Swing_2182", "Outer_Wall_Quart_Door_130", "Outer_Wall_Half_119", "Outer_Wall_Quart_Win_4", "Outer_Wall_Quart_Win_5", "Outer_Wall_Quart_Win_6", "Outer_Wall_Quart_Win_7", "Outer_Wall_Quart_Win_2", "Outer_Wall_Quart_Win_3", "Outer_Wall_Quart_Floor_250", "Outer_Wall_Half_Win_9", "Outer_Wall_Half_Win_8", "Outer_Wall_Half_Win_3", "Outer_Wall_Half_Win_2", "Outer_Wall_Half_Win_7", "Outer_Wall_Half_Win_6", "Outer_Wall_Half_Win_5", "Outer_Wall_Half_Win_4", "Outer_Wall_quart_Win_450", "Outer_Wall_Quart_Floor_598", "Outer_Wall_Quart_Floor_117", "Outer_Wall_Quart_Floor_93", "Outer_Wall_Quart_Garage_01_248", "Outer_Wall_Half_Win_84", "Outer_Wall_Half_Win_85", "Outer_Wall_Half_Win_87", "Outer_Wall_Half_Win_80", "Outer_Wall_Half_Win_81", "Outer_Wall_Half_Win_83", "Outer_Wall_Half_Win_88", "Outer_Wall_Half_Win_89", "Outer_Wall_Half_Door_01_324", "Outer_Wall_Quart_Win_22", "Outer_Wall_Quart_Win_21", "Outer_Door_Swing_482", "Outer_Wall_Half_Door_92", "Outer_Wall_Half_Door_98", "Outer_Wall_Quart_Floor_54", "Outer_Wall_Half_Win_184", "Outer_Wall_Half_Garage_43", "Outer_Door_Swing_4661", "Outer_Wall_Half_Win_525", "Outer_Wall_Quart_Floor_108", "Outer_Wall_Half_Win_92", "Outer_Wall_Half_Win_91", "Outer_Wall_Half_Win_90", "Outer_Wall_Half_Win_97", "Outer_Wall_Half_Win_96", "Outer_Wall_Half_Win_95", "Outer_Wall_Half_Win_94", "Outer_Wall_Half_Win_99", "Outer_Wall_Half_Win_98", "Outer_Door_Swing_01_C_15", "Outer_Door_Swing_01_C_14", "Outer_Door_Swing_01_C_13", "Outer_Door_Swing_01_C_11", "Outer_Door_Swing_01_C_10", "Outer_Door_Swing_8929", "Outer_Wall_Quart_Win_33", "Outer_Wall_Half_25", "Outer_Door_Swing_01_C_9", "Outer_Door_Swing_01_C_8", "Outer_Wall_Half_Door_40", "Outer_Wall_Quart_Floor_24", "Outer_Wall_Quart_Floor_27", "Outer_Wall_Quart_Floor_26", "Outer_Wall_Quart_Floor_20", "Outer_Wall_Half_Door_45", "Outer_Wall_Quart_Floor_29", "Outer_Wall_Quart_Win_02_162", "Outer_Door_Swing_9320", "Outer_Wall_8th_Win_2", "Outer_Door_Swing_10352", "Outer_Wall_Half_Win_120", "Outer_Wall_Half_Win_121", "Outer_Door_Swing_5815", "Outer_Wall_Half_Win_126", "Outer_Wall_Half_Win_127", "Outer_Wall_Half_Win_124", "Outer_Wall_Half_Win_125", "Outer_Wall_Quart_Floor_01_159", "Outer_Wall_Half_Door_110", "Outer_Wall_Quart_Garage_123", "Outer_Wall_Half_Win_68", "Outer_Wall_Half_Win_69", "Outer_Wall_Half_Win_66", "Outer_Wall_Half_Win_67", "Outer_Wall_Half_Win_64", "Outer_Wall_Half_Win_65", "Outer_Wall_Half_Win_62", "Outer_Wall_Half_Win_63", "Outer_Wall_Half_Win_60", "Outer_Wall_Half_Win_61", "Outer_Door_Swing_1375", "Outer_Wall_Half_Win_148", "Outer_Wall_Half_Door_79", "Outer_Wall_Quart_Floor_30", "Outer_Wall_Quart_Floor_31", "Outer_Door_Swing_686", "Outer_Wall_Half_18", "Outer_Wall_Half_12", "Outer_Wall_Half_13", "Outer_Wall_Half_10", "Outer_Wall_Half_16", "Outer_Wall_Half_17", "Outer_Wall_Half_15", "Outer_Door_Swing_3723", "Outer_Wall_16th_01_68", "Outer_Wall_Half_Door_104", "Outer_Wall_Half_Win_150", "Outer_Wall_Half_Win_79", "Outer_Wall_Half_Win_78", "Outer_Wall_Half_Win_75", "Outer_Wall_Half_Win_74", "Outer_Wall_Half_Win_76", "Outer_Wall_Half_Win_71", "Outer_Wall_Half_Win_70", "Outer_Wall_Half_Win_73", "Outer_Wall_Half_Win_72", "Outer_Wall_Half_Door_17", "Outer_Wall_Quart_Win_16", "Outer_Wall_Quart_Win_14", "Outer_Wall_Quart_Win_15", "Outer_Wall_Quart_Win_13", "Outer_Wall_Quart_Win_10", "Outer_Wall_Quart_Win_11", "Outer_Wall_Quart_Win_01_133", "Outer_Wall_Half_Win_159", "Outer_Wall_Half_Win_158", "Outer_Wall_Half_Win_156", "Outer_Wall_Half_Win_155", "Outer_Wall_Half_Win_154", "Outer_Wall_Half_Win_152", "Outer_Door_Swing_4302", "Outer_Wall_Quart_12", "Outer_Wall_8th_2", "Outer_Door_Swing_1370", "Outer_Wall_Quart_Base_01_63", "Outer_Wall_Quart_Floor_7", "Outer_Wall_Quart_Floor_4", "Outer_Wall_Quart_Floor_3", "Outer_Door_Swing_8160", "Outer_Wall_Half_Win_151", "Outer_Wall_Half_101", "Outer_Wall_Half_Win_48", "Outer_Wall_Half_Win_49", "Outer_Wall_Half_Win_40", "Outer_Wall_Half_Win_41", "Outer_Wall_Half_Win_43", "Outer_Wall_Half_Win_44", "Outer_Wall_Half_Win_45", "Outer_Wall_Half_Win_47", "Outer_Wall_Half_Door_19", "Outer_Wall_Quart_Door_4", "Outer_Wall_Quart_Door_2", "Outer_Door_Swing_9663", "Outer_Wall_Half_Door_516", "Outer_Wall_Quart_Floor_5", "Outer_Wall_Quart_Win_65", "Outer_Wall_Half_Door_55", "Outer_Door_Swing_510", "Outer_Wall_Quart_Floor_18", "Outer_Wall_Quart_Floor_14", "Outer_Wall_Quart_Floor_15", "Outer_Wall_Quart_Floor_16", "Outer_Wall_Quart_Floor_17", "Outer_Wall_Quart_Floor_10", "Outer_Wall_Quart_Floor_11", "Outer_Wall_Quart_Floor_13", "Outer_Door_Swing_10838", "Outer_Wall_quart_Win_106", "Outer_Wall_Half_Win_02_115", "Outer_Wall_Half_Apex_01_143", "Outer_Wall_Half_Win_145", "Outer_Wall_Half_Win_146", "Outer_Wall_Half_Win_147", "Outer_Wall_Half_Win_140", "Outer_Wall_Half_Win_141", "Outer_Wall_Half_Win_142", "Outer_Wall_Half_Win_143", "Outer_Wall_Half_38", "Outer_Wall_Half_39", "Outer_Wall_Half_34", "Outer_Wall_Half_35", "Outer_Wall_Half_36", "Outer_Wall_Half_37", "Outer_Wall_Half_30", "Outer_Wall_Half_31", "Outer_Wall_Half_32", "Outer_Wall_Half_33", "Outer_Door_Swing_10169", "Outer_Wall_Half_Win_568", "Outer_Door_Swing_11560", "Outer_Wall_Half_Door_125", "Outer_Door_Swing_346", "Outer_Door_Swing_1045", "Outer_Wall_Half_Win_57", "Outer_Wall_Half_Win_56", "Outer_Wall_Half_Win_55", "Outer_Wall_Half_Win_54", "Outer_Wall_Half_Win_53", "Outer_Wall_Half_Win_52", "Outer_Wall_Half_Win_51", "Outer_Wall_Half_Win_50", "Outer_Wall_16th_133", "Outer_Wall_Half_Win_59", "Outer_Wall_Half_Win_58", "Outer_Door_Swing_478", "Outer_Wall_Quart_Win_71", "Outer_Wall_Half_Door_23", "Outer_Wall_Half_Door_22", "Outer_Wall_Half_Door_21", "Outer_Wall_Half_Door_27", "Outer_Wall_Half_Door_26", "Outer_Wall_Half_Door_24", "Outer_Wall_Half_Door_29", "Outer_Wall_Half_Door_28", "Outer_Wall_Half_Win_175", "Outer_Wall_Half_Win_177", "Outer_Wall_Half_Win_176", "Outer_Wall_Half_Garage_38", "Outer_Wall_Half_Garage_30", "Outer_Door_Swing_01_C_12", "Outer_Wall_Half_23", "Outer_Wall_Half_22", "Outer_Wall_Half_21", "Outer_Wall_Half_20", "Outer_Wall_Half_27", "Outer_Wall_Half_26", "Outer_Wall_Half_24", "Outer_Wall_Half_29", "Outer_Wall_Half_28", "Outer_Wall_Half_Win_42", "Outer_Wall_Half_Win_46", "Outer_Wall_8th_01_61", "Outer_Wall_8th_466", "Outer_Wall_Half_Apex_159", "Outer_Door_Swing_8690", "Outer_Door_Swing_2469", "Outer_Door_Swing_7299", "Outer_Wall_Half_Win_22", "Outer_Wall_Half_Win_23", "Outer_Wall_Half_Win_20", "Outer_Wall_Half_Win_21", "Outer_Wall_Half_Win_26", "Outer_Wall_Half_Win_24", "Outer_Wall_Half_Win_25", "Outer_Door_Swing_402", "Outer_Wall_Half_Win_28", "Outer_Wall_Half_Win_29", "Outer_Wall_Half_Win_161", "Outer_Wall_Half_Garage_01_122", "Outer_Wall_Quart_Win_45", "Outer_Wall_8th_Win_01_142", "Outer_Wall_Half_Win_166", "Outer_Wall_Half_Win_167", "Outer_Wall_Half_Win_160", "Outer_Wall_Half_Win_27", "Outer_Wall_Half_Win_168", "Outer_Wall_Half_104", "Outer_Door_Swing_710", "Outer_Wall_Half_50", "Outer_Wall_8th_77", "Outer_Door_Swing_1615", "Outer_Wall_Quart_01_68", "Outer_Wall_Half_Win_30", "Outer_Wall_Half_Win_33", "Outer_Wall_Half_Win_32", "Outer_Wall_Half_Win_35", "Outer_Wall_Half_Win_34", "Outer_Wall_Half_Win_37", "Outer_Wall_Half_Win_36", "Outer_Wall_Half_Win_39", "Outer_Wall_Half_Win_38", "Outer_Door_Swing_6370", "Outer_Door_Swing_10945", "Outer_Wall_Quart_411", "Outer_Door_Swing_234", "Outer_Wall_Quart_Door_02_36", "Outer_Wall_Half_Win_113", "Outer_Wall_Half_Win_112", "Outer_Wall_Half_Win_111", "Outer_Wall_Half_Win_110", "Outer_Wall_Half_Win_117", "Outer_Wall_Half_Win_116", "Outer_Wall_Half_Win_115", "Outer_Wall_Half_Win_114", "Outer_Wall_Half_Win_119", "Outer_Wall_Half_Win_118", "Outer_Wall_Half_44", "Outer_Wall_Half_41", "Outer_Wall_Half_42", "Outer_Wall_Half_Garage_02_142", "Outer_Door_Swing_10555", "Outer_Door_Swing_8435", "Outer_Wall_Quart_11", "Outer_Wall_Quart_Floor_202", "Outer_Wall_Half_Door_443", "Outer_Door_Swing_6605", "Outer_Wall_Quart_Roof_01_339", "Outer_Wall_Quart_42", "Outer_Wall_Quart_6", "Outer_Wall_Quart_5", "Outer_Wall_Quart_4", "Outer_Wall_Quart_9", "Outer_Wall_Half_Door_13", "Outer_Wall_Half_Door_10", "Outer_Wall_Half_Door_11", "Outer_Wall_Half_Door_16", "Outer_Wall_quart_Win_27", "Outer_Wall_quart_Win_26", "Outer_Wall_quart_Win_25", "Outer_Wall_Half_Win_100", "Outer_Wall_Half_Win_101", "Outer_Wall_Half_Win_102", "Outer_Wall_Half_Win_104", "Outer_Wall_Half_Win_106", "Outer_Wall_Half_Win_107", "Outer_Wall_Half_Win_108", "Outer_Wall_Half_Win_109", "Outer_Wall_Quart_Base_67", "Outer_Wall_Quart_Door_01_147", "Outer_Wall_Quart_Garage_257", "Outer_Wall_Quart_Floor_187", "Outer_Wall_16th_5", "Outer_Wall_16th_2", "Outer_Wall_Quart_Floor_219", "Outer_Wall_Half_Win_149", "Outer_Wall_Half_Win_19", "Outer_Wall_Half_Win_18", "Outer_Wall_Half_Win_13", "Outer_Wall_Half_Win_12", "Outer_Wall_Half_Win_11", "Outer_Wall_Half_Win_10", "Outer_Wall_Half_Win_17", "Outer_Wall_Half_Win_15", "Outer_Wall_Half_Win_14", "Outer_Door_Swing_7805", "Outer_Wall_Quart_23", "Outer_Wall_Half_Win_139", "Outer_Wall_Half_Win_138", "Outer_Wall_Half_Win_135", "Outer_Wall_Half_Win_134", "Outer_Wall_Half_Win_137", "Outer_Wall_Half_Win_136", "Outer_Wall_Half_Win_131", "Outer_Wall_Half_Win_130", "Outer_Wall_Half_Win_133", "Outer_Wall_Half_Win_132", "Outer_Wall_Half_Win_31", "Outer_Door_Swing_2713", "Outer_Wall_Half_Win_313", "Outer_Wall_Half_164", "Outer_Wall_Quart_Floor_152", "Outer_Wall_Quart_Floor_155", "Outer_Wall_Half_Door_8", "Outer_Wall_Half_Door_3", "Outer_Wall_Half_Door_5", "Outer_Wall_Half_Door_7", "Outer_Wall_Quart_Base_2", "Outer_Door_Swing_9946", "Outer_Wall_Half_8", "Outer_Wall_Half_9", "Outer_Wall_Half_Win_128", "Outer_Wall_Half_Win_129", "Outer_Wall_Half_Win_122", "Outer_Wall_Half_Win_123", "Outer_Wall_Half_2", "Outer_Wall_Half_3", "Outer_Wall_Half_4", "Outer_Wall_Half_6", "Outer_Wall_Half_7", "Outer_Door_Swing_286", "Outer_Door_Swing_1096", "Outer_Wall_Half_Apex_566", "Outer_Wall_Half_01_16", "Outer_Wall_Quart_Garage_461", "Outer_Door_Swing_897", "Outer_Wall_Quart_213", "Outer_Wall_Half_205", "Outer_Wall_Quart_Door_03_56", "Outer_Door_Swing_525", "Outer_Door_Swing_12", "Outer_Door_Swing_294", "Outer_Wall_Half_11", "Outer_Wall_Half_14", "Outer_Door_Swing_5168", "Outer_Door_Swing_3080", "Outer_Wall_Half_Win_162", "Outer_Wall_Half_Win_86", "Outer_Wall_Half_Win_82"], "Bench": ["Bench_23", "Bench_01_53", "Bench_71", "Bench_25", "Bench_66", "Bench_60", "Bench_69", "Bench_56", "Bench_197", "Bench_181", "Bench_183", "Bench_188", "Bench_195", "Bench_192", "Bench_18", "Bench_15", "Bench_13", "Bench_10", "Bench_11", "Bench_16", "Bench_84", "Bench_184", "Bench_4", "Bench_3", "Bench_228", "Bench_63", "Bench_32"], "Paint": ["Paint_Can_01_4", "Paint_Can_23", "Paint_Can_721", "Paint_Can_724", "Paint_Can_287", "Paint_Can_295", "Paint_Can_298", "Paint_Can_14", "Paint_Can_17", "Paint_Can_9", "Paint_Can_21", "Paint_Can_22", "Paint_Can_8", "Paint_Can_16", "Paint_Can_15", "Paint_Can_11", "Paint_Can_10", "Paint_Can_13", "Paint_Can_12", "Paint_Can_18", "Paint_Can_27", "Paint_Can_3", "Paint_Can_5", "Paint_Can_4", "Paint_Can_7", "Paint_Can_6", "Paint_Can_26"], "Lamp": ["Lamp_01_46", "Lamp_277", "Lamp_90", "Lamp_93", "Lamp_103", "Lamp_9", "Lamp_32", "Lamp_221", "Lamp_218", "Lamp_40"], "Book": ["Book_2", "Book_3", "Book_6", "Book_4", "Book_5", "Book_01_30", "Book_72", "Book_184"], "Curtain": ["Curtain_78", "Curtain_93", "Curtain_79", "Curtain_29", "Curtain_28", "Curtain_25", "Curtain_24", "Curtain_27", "Curtain_26", "Curtain_21", "Curtain_132", "Curtain_6", "Curtain_51", "Curtain_13", "Curtain_14", "Curtain_15", "Curtain_17", "Curtain_18", "Curtain_19", "Curtain_01_29", "Curtain_135", "Curtain_03_39", "Curtain_84", "Curtain_82", "Curtain_22", "Curtain_50", "Curtain_121", "Curtain_125", "Curtain_138", "Curtain_54", "Curtain_4", "Curtain_59", "Curtain_98", "Curtain_99", "Curtain_90", "Curtain_91", "Curtain_92", "Curtain_95", "Curtain_97", "Curtain_104", "Curtain_107", "Curtain_106", "Curtain_101", "Curtain_100", "Curtain_103", "Curtain_89", "Curtain_88", "Curtain_111", "Curtain_117", "Curtain_114", "Curtain_55", "Curtain_60", "Curtain_62", "Curtain_56", "Curtain_64", "Curtain_66", "Curtain_57", "Curtain_58", "Curtain_167", "Curtain_126", "Curtain_63", "Curtain_65", "Curtain_171", "Curtain_130", "Curtain_136", "Curtain_73", "Curtain_71", "Curtain_74", "Curtain_70", "Curtain_141", "Curtain_142", "Curtain_145", "Curtain_149", "Curtain_148", "Curtain_8", "Curtain_02_75", "Curtain_9", "Curtain_76", "Curtain_43", "Curtain_42", "Curtain_40", "Curtain_47", "Curtain_77", "Curtain_154", "Curtain_87", "Curtain_152", "Curtain_85", "Curtain_33", "Curtain_75", "Curtain_81", "Curtain_36", "Curtain_37", "Curtain_34", "Curtain_35", "Curtain_32", "Curtain_30"], "Cladding": ["Cladding_Edge_4", "Cladding_Edge_5", "Cladding_Edge_6", "Cladding_Edge_7", "Cladding_Edge_2", "Cladding_Edge_3", "Cladding_Edge_8", "Cladding_Edge_9", "Cladding_Edge_49", "Cladding_Edge_46", "Cladding_Edge_40", "Cladding_Edge_43", "Cladding_Edge_64", "Cladding_Edge_11", "Cladding_Edge_01_12", "Cladding_Edge_19", "Cladding_Edge_16", "Cladding_Edge_15", "Cladding_Edge_12", "Cladding_Edge_10", "Cladding_Edge_30", "Cladding_Edge_31", "Cladding_Edge_32", "Cladding_Edge_33", "Cladding_Edge_34", "Cladding_Edge_37", "Cladding_Edge_13", "Cladding_Edge_29", "Cladding_Edge_28", "Cladding_Edge_27", "Cladding_Edge_26", "Cladding_Edge_17", "Cladding_Edge_52", "Cladding_Edge_56"], "BRPlayer": ["BRPlayer_34", "BRPlayer_01_96", "BRPlayer_36"], "Porch": ["Porch_Middle_34", "Porch_Middle_30", "Porch_Pillar_18", "Porch_Pillar_19", "Porch_Pillar_17", "Porch_Middle_7", "Porch_Middle_6", "Porch_Middle_3", "Porch_Middle_8", "Porch_Pillar_12", "Porch_Pillar_25", "Porch_Pillar_24", "Porch_Pillar_26", "Porch_Pillar_21", "Porch_Pillar_20", "Porch_Corner_455", "Porch_Middle_10", "Porch_Middle_14", "Porch_Middle_16", "Porch_Pillar_39", "Porch_Pillar_37", "Porch_Corner_4", "Porch_Pillar_27", "Porch_Pillar_73", "Porch_Middle_01_19", "Porch_Corner_77", "Porch_Banister_8th_01_31", "Porch_Pillar_470", "Porch_Pillar_176", "Porch_Pillar_401", "Porch_Middle_4", "Porch_Corner_33", "Porch_Pillar_28", "Porch_Middle_52", "Porch_Pillar_40", "Porch_Pillar_9", "Porch_Pillar_23", "Porch_Pillar_22", "Porch_Pillar_83", "Porch_Pillar_86", "Porch_Pillar_85", "Porch_Pillar_44", "Porch_Pillar_01_24", "Porch_Pillar_405", "Porch_Middle_458", "Porch_Middle_307", "Porch_Pillar_4", "Porch_Pillar_16", "Porch_Pillar_45", "Porch_Pillar_43", "Porch_Middle_57", "Porch_Pillar_41", "Porch_Banister_8th_2", "Porch_Corner_3", "Porch_Corner_2", "Porch_Corner_8", "Porch_Corner_10", "Porch_Pillar_51", "Porch_Pillar_410", "Porch_Pillar_35", "Porch_Pillar_33", "Porch_Pillar_31", "Porch_Pillar_29", "Porch_Pillar_397", "Porch_Pillar_399", "Porch_Middle_5_Blueprint", "Porch_Pillar_46", "Porch_Pillar_42", "Porch_Pillar_407", "Porch_Corner_01_417"], "Bookcase": ["Bookcase_3", "Bookcase_01_21", "Bookcase_02_27", "Bookcase_774", "Bookcase_23"], "6": ["6"], "Tft": ["Tft_01_258"], "Fireplace": ["Fireplace_96", "Fireplace_01_787"], "Chimney": ["Chimney_Base_20", "Chimney_Mid_8", "Chimney_Mid_7", "Chimney_Mid_5", "Chimney_Mid_2", "Chimney_Mid_3", "Chimney_Base_121", "Chimney_Base_112", "Chimney_Base_116", "Chimney_Mid_01_103", "Chimney_Base_19", "Chimney_Roof_190", "Chimney_Base_114", "Chimney_Base_01_82", "Chimney_Mid_187", "Chimney_Base_127", "Chimney_Base_107", "Chimney_Base_02_93", "Chimney_Base_8", "Chimney_Base_9", "Chimney_Base_6", "Chimney_Base_134", "Chimney_Base_130", "Chimney_Base_17", "Chimney_Base_14", "Chimney_Base_12", "Chimney_Base_13", "Chimney_Base_10", "Chimney_Base_88", "Chimney_Mid_137", "Chimney_Roof_01_140", "Chimney_Base_184"], "4": ["4"], "Flor": ["Flor_3", "Flor_4", "Flor_01_156", "Flor_145"], "Bed": ["Bed_Double_119", "Bed_Double_01_116", "Bed_Double_6", "Bed_Double_02_729", "Bed_Double_237", "Bed_Double_735", "Bed_Double_732"], "Small": ["Small_House_40", "Small_House_13", "Small_House_10", "Small_House_28", "Small_House_27", "Small_House_26", "Small_House_25", "Small_House_19", "Small_House_23", "Small_House_22", "Small_House_20", "Small_House_17128", "Small_House_36", "Small_House_46", "Small_House_48", "Small_House_43", "Small_House_45", "Small_House_44", "Small_House_47", "Small_House_3", "Small_House_8", "Small_House_29", "Small_House_4661", "Small_House_7", "Small_House_42", "Small_House_11630", "Small_House_41", "Small_House_01", "Small_House_15", "Small_House_11", "Small_House_18", "Small_House_24", "Small_House_30", "Small_House_31", "Small_House_33", "Small_House_34", "Small_House_37", "Small_House_38", "Small_House_39"], "Road": ["Road_102", "Road_104", "Road_99", "Road_98", "Road_91", "Road_90", "Road_93", "Road_95", "Road_94", "Road_97", "Road_96", "Road_7", "Road_3", "Road_86", "Road_87", "Road_84", "Road_85", "Road_82", "Road_83", "Road_80", "Road_88", "Road_89", "Road_79", "Road_78", "Road_37", "Road_36", "Road_35", "Road_34", "Road_33", "Road_32", "Road_31", "Road_30", "Road_39", "Road_38", "Road_24", "Road_25", "Road_26", "Road_27", "Road_20", "Road_21", "Road_22", "Road_23", "Road_28", "Road_29", "Road_100", "Road_101", "Road_106", "Road_105", "Road_6", "Road_11", "Road_10", "Road_13", "Road_12", "Road_15", "Road_14", "Road_17", "Road_19", "Road_18", "Road_68", "Road_73", "Road_72", "Road_71", "Road_70", "Road_77", "Road_76", "Road_75", "Road_74", "Road_69", "Road_60", "Road_61", "Road_62", "Road_63", "Road_65", "Road_66", "Road_67", "Road_5", "Road_4", "Road_55", "Road_54", "Road_57", "Road_56", "Road_51", "Road_50", "Road_53", "Road_52", "Road_2", "Road_59", "Road_58", "Road_9", "Road_8", "Road_42", "Road_43", "Road_40", "Road_41", "Road_46", "Road_47", "Road_44", "Road_45", "Road_49", "Road_103"], "11": ["11"], "10": ["10"], "13": ["13_26"], "12": ["12"], "15": ["15"], "14": ["14"], "Fence": ["Fence_137", "Fence_134", "Fence_133", "Fence_132", "Fence_131", "Fence_138", "Fence_313", "Fence_183", "Fence_136", "Fence_82", "Fence_635", "Fence_637", "Fence_130", "Fence_129", "Fence_139", "Fence_185", "Fence_182", "Fence_85", "Fence_89", "Fence_198", "Fence_727", "Fence_153", "Fence_777", "Fence_159", "Fence_158", "Fence_155", "Fence_157", "Fence_156", "Fence_151", "Fence_152", "Fence_796", "Fence_164", "Fence_165", "Fence_166", "Fence_161", "Fence_91", "Fence_90", "Fence_93", "Fence_92", "Fence_94", "Fence_97", "Fence_96", "Fence_200", "Fence_203", "Fence_202", "Fence_205", "Fence_204", "Fence_207", "Fence_206", "Fence_186", "Fence_258", "Fence_259", "Fence_126", "Fence_127", "Fence_199", "Fence_148", "Fence_149", "Fence_144", "Fence_145", "Fence_142", "Fence_143", "Fence_140", "Fence_141", "Fence_116", "Fence_219", "Fence_212", "Fence_216", "Fence_217", "Fence_214", "Fence_47", "Fence_719", "Fence_189", "Fence_173", "Fence_171", "Fence_170", "Fence_177", "Fence_175", "Fence_174", "Fence_179", "Fence_178", "Fence_187", "Fence_184", "Fence_191", "Fence_193", "Fence_192", "Fence_195", "Fence_194", "Fence_197", "Fence_229", "Fence_228", "Fence_227", "Fence_225", "Fence_224", "Fence_223", "Fence_222", "Fence_233", "Fence_235", "Fence_237", "Fence_238", "Fence_239", "Fence_72", "Fence_4", "Fence_7", "Fence_168", "Fence_188", "Fence_180", "Fence_181", "Fence_58", "Fence_230", "Fence_231", "Fence_234", "Fence_28", "Fence_29", "Fence_20", "Fence_21", "Fence_22", "Fence_24", "Fence_25", "Fence_26", "Fence_27", "Fence_5", "Fence_3", "Fence_2", "Fence_9", "Fence_8", "Fence_77", "Fence_245", "Fence_244", "Fence_247", "Fence_246", "Fence_240", "Fence_243", "Fence_242", "Fence_39", "Fence_38", "Fence_33", "Fence_32", "Fence_30", "Fence_37", "Fence_35", "Fence_34", "Fence_117", "Fence_78", "Fence_128", "Fence_120", "Fence_121", "Fence_122", "Fence_218", "Fence_123", "Fence_124", "Fence_125", "Fence_211", "Fence_256", "Fence_257", "Fence_254", "Fence_255", "Fence_252", "Fence_253", "Fence_250", "Fence_251", "Fence_6", "Fence_640", "Fence_646", "Fence_649", "Fence_261", "Fence_260", "Fence_10", "Fence_13", "Fence_12", "Fence_15", "Fence_14", "Fence_17", "Fence_19", "Fence_18", "Fence_11", "Fence_16", "Fence_87", "Fence_84", "Fence_83", "Fence_80", "Fence_01_233", "Fence_88", "Fence_108", "Fence_64", "Fence_65", "Fence_66", "Fence_67", "Fence_60", "Fence_61", "Fence_62", "Fence_63", "Fence_68", "Fence_69", "Fence_700", "Fence_215", "Fence_76", "Fence_75", "Fence_74", "Fence_73", "Fence_71", "Fence_70", "Fence_79", "Fence_176", "Fence_645", "Fence_676", "Fence_241", "Fence_321", "Fence_249", "Fence_31", "Fence_232", "Fence_236", "Fence_675", "Fence_48", "Fence_43", "Fence_40", "Fence_41", "Fence_46", "Fence_44", "Fence_45", "Fence_111", "Fence_167", "Fence_160", "Fence_110", "Fence_113", "Fence_112", "Fence_115", "Fence_114", "Fence_119", "Fence_118", "Fence_196", "Fence_163", "Fence_333", "Fence_59", "Fence_55", "Fence_54", "Fence_56", "Fence_50", "Fence_53", "Fence_52", "Fence_150", "Fence_86", "Fence_226", "Fence_221", "Fence_172", "Fence_81", "Fence_102", "Fence_103", "Fence_106", "Fence_107", "Fence_104", "Fence_105", "Fence_109", "Fence_213", "Fence_210", "Fence_49", "Fence_209"], "16": ["16"], "Wall": ["Wall_Low_74", "Wall_Low_End_60", "Wall_Low_End_64", "Wall_Low_396", "Wall_Low_45", "Wall_Low_44", "Wall_Low_47", "Wall_Low_46", "Wall_Low_41", "Wall_Low_40", "Wall_Low_43", "Wall_Low_42", "Wall_Low_End_193", "Wall_Low_End_326", "Wall_Low_End_387", "Wall_Low_Quart_8", "Wall_Low_161", "Wall_Low_57", "Wall_Low_54", "Wall_Low_58", "Wall_Low_59", "Wall_Low_62", "Wall_Low_End_287", "Wall_Low_End_284", "Wall_Low_60", "Wall_Low_67", "Wall_Low_End_82", "Wall_Low_26", "Wall_Low_24", "Wall_Low_23", "Wall_Low_22", "Wall_Low_21", "Wall_Low_20", "Wall_Low_29", "Wall_Low_49", "Wall_Low_Half_01_237", "Wall_Low_End_343", "Wall_Low_End_346", "Wall_Low_End_344", "Wall_Low_End_299", "Wall_Low_290", "Wall_Low_34", "Wall_Low_35", "Wall_Low_36", "Wall_Low_37", "Wall_Low_30", "Wall_Low_31", "Wall_Low_32", "Wall_Low_33", "Wall_Low_38", "Wall_Low_End_18", "Wall_Low_End_194", "Wall_Low_63", "Wall_Low_27", "Wall_Low_End_405", "Wall_Low_28", "Wall_Low_136", "Wall_Low_61", "Wall_Low_Half_352", "Wall_Low_Half_358", "Wall_Low_End_48", "Wall_Low_End_47", "Wall_Low_End_46", "Wall_Low_End_45", "Wall_Low_End_44", "Wall_Low_End_43", "Wall_Low_End_42", "Wall_Low_End_40", "Wall_Low_End_185", "Wall_Low_Quart_372", "Wall_Low_349", "Wall_Low_52", "Wall_Low_Half_293", "Wall_Low_8th_01_277", "Wall_Low_17", "Wall_Low_15", "Wall_Low_13", "Wall_Low_10", "Wall_Low_End_50", "Wall_Low_End_51", "Wall_Low_End_52", "Wall_Low_End_170", "Wall_Low_End_173", "Wall_Low_End_177", "Wall_Low_End_312", "Wall_Low_339", "Wall_Low_331", "Wall_Low_End_65", "Wall_Low_8", "Wall_Low_9", "Wall_Low_4", "Wall_Low_6", "Wall_Low_7", "Wall_Low_2", "Wall_Low_Half_9", "Wall_Low_End_309", "Wall_Low_End_306", "Wall_Low_Quart_353", "Wall_Low_01_219", "Wall_Low_322", "Wall_Low_Quart_01_366", "Wall_Low_Quart_167", "Wall_Low_End_59", "Wall_Low_End_56", "Wall_Low_End_335", "Wall_Low_Half_174", "Wall_Low_Quart_82", "Wall_Low_Quart_190", "Wall_Low_End_2", "Wall_Low_End_6", "Wall_Low_End_7", "Wall_Low_End_142", "Wall_Low_Quart_6", "Wall_Low_End_20", "Wall_Low_End_12", "Wall_Low_End_13", "Wall_Low_End_15", "Wall_Low_End_19", "Wall_Low_Quart_384", "Wall_Low_End_178", "Wall_Low_End_108", "Wall_Low_8th_296", "Wall_Low_Half_8", "Wall_Low_Half_152", "Wall_Low_End_29", "Wall_Low_End_28", "Wall_Low_End_25", "Wall_Low_End_27", "Wall_Low_End_23", "Wall_Low_End_22", "Wall_Low_Half_5", "Wall_Low_Quart_139", "Wall_Low_End_74", "Wall_Low_End_38", "Wall_Low_End_39", "Wall_Low_End_30", "Wall_Low_End_31", "Wall_Low_End_36", "Wall_Low_End_37", "Wall_Low_End_62", "Wall_Low_Quart_122", "Wall_Low_End_111", "Wall_Low_8th_368", "Wall_Low_End_01_243", "Wall_Low_227", "Wall_Low_223", "Wall_Low_End_61", "Wall_Low_159", "Wall_Low_53", "Wall_Low_51", "Wall_Low_End_375", "Wall_Low_55", "Wall_Low_Quart_33", "Wall_Low_Quart_182"], "House": ["House_Base_Quart_96", "House_Base_Quart_62", "House_Base_Quart_32", "House_Base_Quart_8", "House_Base_Quart_7", "House_Base_Quart_386", "House_Base_Quart_01_374", "House_Base_Quart_31", "House_Base_Quart_6", "House_Base_Quart_19", "House_Base_Quart_18", "House_Base_Quart_13", "House_Base_Quart_12", "House_Base_Quart_11", "House_Base_Quart_10", "House_Base_Quart_17", "House_Base_Quart_16", "House_Base_Quart_15", "House_Base_Quart_14", "House_Base_Quart_41", "House_Base_Quart_23", "House_Base_Quart_20", "House_Base_Quart_3", "House_Base_Quart_2", "House_Base_Quart_5", "House_Base_Quart_4", "House_Base_Quart_122", "House_Base_Quart_50", "House_Base_Quart_44", "House_Base_Quart_47", "House_Base_Quart_42", "House_Base_Quart_43", "House_Base_Quart_48", "House_Base_Quart_49", "House_Base_Quart_21"], "InstancedFoliageActor": ["InstancedFoliageActor_0"], "Plug": ["Plug_Socket_01_73", "Plug_Socket_77", "Plug_Socket_22", "Plug_Socket_8", "Plug_Socket_2", "Plug_Socket_4", "Plug_Socket_6", "Plug_Socket_7"], "Cube2": ["Cube2"], "Basketball": ["Basketball_Hoop_178", "Basketball_Hoop_5", "Basketball_Hoop_12", "Basketball_Hoop_01_424", "Basketball_Hoop_9", "Basketball_Hoop_204"], "Floor": ["Floor_Half_Basic_01_114", "Floor_01_Basic94", "Floor_01_Basic95", "Floor_01_Basic96", "Floor_01_Basic97", "Floor_01_Basic90", "Floor_01_Basic92", "Floor_01_Basic99", "Floor_8th_01_159", "Floor_Half_Half_5", "Floor_01_Basic87", "Floor_01_Basic85", "Floor_01_Basic84", "Floor_01_Basic83", "Floor_01_Basic81", "Floor_01_Basic80", "Floor_01_Basic89", "Floor_01_Basic88", "Floor__8th_8th_9", "Floor_Half_02_414", "Floor_11", "Floor__8th_8th_01_42", "Floor_Quart_6", "Floor_Quart_2", "Floor_Quart_3", "Floor_94", "Floor_01_Basic50", "Floor_01_Basic51", "Floor_01_Basic53", "Floor_01_Basic54", "Floor_01_Basic55", "Floor_01_Basic56", "Floor_01_Basic57", "Floor_01_Basic58", "Floor_01_Basic59", "Floor_Half_18", "Floor_01_Basic93_810", "Floor_01_Basic82_91", "Floor_Half_Basic_83", "Floor_01_Basic43", "Floor_01_Basic41", "Floor_01_Basic40", "Floor_01_Basic47", "Floor_01_Basic45", "Floor_01_Basic44", "Floor_01_Basic49", "Floor_01_Basic48", "Floor_8th__01_39", "Floor_01_Basic63", "Floor_01_Basic65", "Floor_01_Basic66", "Floor_01_Basic76", "Floor_01_Basic77", "Floor_01_Basic74", "Floor_01_Basic75", "Floor_01_Basic72", "Floor_01_Basic73", "Floor_01_Basic70", "Floor_01_Basic71", "Floor_01_Basic79", "Floor_Half_Basic_439", "Floor_01_Basic30_40", "Floor_01_Basic69", "Floor_01_Basic61", "Floor_01_Basic60", "Floor_01_Basic64", "Floor_01_Basic67", "Floor_Half_Half_15", "Floor_Half_4", "Floor_01_Basic10", "Floor_01_Basic11", "Floor_01_Basic12", "Floor_01_Basic13", "Floor__8th_8th_10", "Floor_01_Basic_109", "Floor_Half_01_256", "Floor__8th_8th_392", "Floor_01_Basic32", "Floor_01_Basic31", "Floor_01_Basic36", "Floor_01_Basic37", "Floor_01_Basic35", "Floor_01_Basic38", "Floor_01_Basic39", "Floor__8th_8th_8", "Floor__8th_8th_4", "Floor__8th_8th_5", "Floor__8th_8th_2", "Floor__8th_8th_3", "Floor__8th_8th_7", "Floor_01_Basic25", "Floor_01_Basic14", "Floor_01_Basic29", "Floor_01_Basic28", "Floor_Quart_167", "Floor_Half_Half_2", "Floor_Half_Half_6", "Floor_Half_Half_7", "Floor_Half_Half_4", "Floor_16", "Floor_Quart_5", "Floor_10", "Floor_8", "Floor_9", "Floor_6", "Floor_7", "Floor_2", "Floor_01_Basic68_150", "Floor_8th_2", "Floor_Half_32", "Floor_Half_Basic_14", "Floor_Half_Basic_10", "Floor_Half_Basic_12", "Floor_Half_Basic_13", "Floor_112", "Floor_Half_Basic_6", "Floor_Half_Basic_7", "Floor_Half_Basic_4", "Floor_Half_Basic_5", "Floor_Half_Basic_8", "Floor_Half_Basic_9", "Floor_Half_20", "Floor_Half_Stairs_11", "Floor_01_Basic8", "Floor_01_Basic9", "Floor_01_Basic2", "Floor_01_Basic3", "Floor_01_Basic6", "Floor_01_Basic7", "Floor_01_Basic4", "Floor_01_Basic5", "Floor_01_Basic33_99", "Floor_Half_26", "Floor_Half_Half_01_118", "Floor_Quart_01_537", "Floor_Half_22", "Floor_01_Basic46_309", "Floor_Half_19", "Floor_Half_10", "Floor_Half_17", "Floor_01_Basic42_81", "Floor_Half_9", "Floor_Half_8", "Floor_Half_7", "Floor_Half_6", "Floor_Half_5", "Floor_Half_3", "Floor_Basic_01_6", "Floor_01_Basic52_113", "Floor_01_Basic27", "Floor_01_Basic78_309", "Floor_01_Basic101", "Floor_01_Basic100", "Floor_01_Basic103", "Floor_01_Basic102", "Floor_Half_Stairs_01_32", "Floor_01_80", "Floor_01_Basic91_808", "Floor_Half_Basic_2"], "Oak": ["Oak_03_30", "Oak_136"], "SkySphere": ["SkySphere"], "Dufflebag": ["Dufflebag_760", "Dufflebag_706", "Dufflebag_01_61"], "Garden": ["Garden_Tressel_6", "Garden_Tressel_13", "Garden_Tressel_17", "Garden_Tressel_90", "Garden_Tressel_97", "Garden_Chair_18", "Garden_Chair_19", "Garden_Chair_10", "Garden_Chair_11", "Garden_Chair_12", "Garden_Chair_13", "Garden_Chair_14", "Garden_Chair_15", "Garden_Chair_16", "Garden_Chair_17", "Garden_Tressel_88", "Garden_Tressel_82", "Garden_Tressel_80", "Garden_Tressel_87", "Garden_Tressel_85", "Garden_Tressel_02_148", "Garden_Chair_210", "Garden_Rocks_01_76", "Garden_Chair_25", "Garden_Chair_24", "Garden_Chair_27", "Garden_Chair_26", "Garden_Chair_21", "Garden_Chair_20", "Garden_Chair_23", "Garden_Chair_22", "Garden_Chair_29", "Garden_Chair_28", "Garden_Tressel_496", "Garden_Tressel_154", "Garden_Tressel_157", "Garden_Chair_32", "Garden_Chair_33", "Garden_Chair_30", "Garden_Chair_31", "Garden_Chair_36", "Garden_Chair_37", "Garden_Chair_34", "Garden_Chair_35", "Garden_Chair_38", "Garden_Chair_39", "Garden_Chair_207", "Garden_Tressel_162", "Garden_Chair_171", "Garden_Chair_178", "Garden_Tressel_176", "Garden_Tressel_175", "Garden_Tressel_174", "Garden_Tressel_172", "Garden_Tressel_171", "Garden_Chair_181", "Garden_Tressel_4", "Garden_Tressel_7", "Garden_Tressel_8", "Garden_Tressel_14", "Garden_Tressel_19", "Garden_Tressel_216", "Garden_Tressel_5", "Garden_Rocks_6", "Garden_Rocks_71", "Garden_Rocks_74", "Garden_Rocks_3", "Garden_Rocks_2", "Garden_Rocks_7", "Garden_Rocks_5", "Garden_Rocks_4", "Garden_Tressel_33", "Garden_Tressel_31", "Garden_Chair_134", "Garden_Chair_137", "Garden_Chair_3", "Garden_Chair_7", "Garden_Tressel_01_151", "Garden_Chair_8", "Garden_Chair_9", "Garden_Chair_01_4", "Garden_Tressel_29", "Garden_Tressel_20", "Garden_Tressel_23", "Garden_Rocks_12", "Garden_Rocks_11", "Garden_Chair_47", "Garden_Chair_40", "Garden_Chair_2", "Garden_Chair_6", "Garden_Chair_4", "Garden_Chair_5", "Garden_Chair_50", "Garden_Rocks_8", "Garden_Tressel_35", "Garden_Tressel_38", "Garden_Tressel_182", "Garden_Tressel_73", "Garden_Tressel_76", "Garden_Tressel_79"], "Power": ["Power_Line_3", "Power_Line_2", "Power_Line_5", "Power_Line_4", "Power_Line_7", "Power_Line_6", "Power_Line_9", "Power_Line_8", "Power_Line_Connector_01_53", "Power_Line_Connector_65", "Power_Line_Cable_Single_01_32", "Power_Line_19", "Power_Line_18", "Power_Line_11", "Power_Line_13", "Power_Line_15", "Power_Line_14", "Power_Line_17", "Power_Line_16", "Power_Line_Cable_Single_38", "Power_Line_Cable_01_Spline_607", "Power_Line_20", "Power_Line_21", "Power_Line_24", "Power_Line_28", "Power_Line_01_59", "Power_Line_Cable_Single_4", "Power_Line_Cable_Single_3", "Power_Line_Cable_Single_2", "Power_Line_Connector_56", "Power_Line_Connector_59", "Power_Line_Connector_71", "Power_Line_610", "Power_Line_Cable_Single_41", "Power_Line_Cable_Single_47", "Power_Line_Connector_68", "Power_Line_Connector_62", "Power_Line_604", "Power_Line_Cable_Single_44"], "Cube3": ["Cube3"], "Stop": ["Stop_Sign_19", "Stop_Sign_11", "Stop_Sign_22", "Stop_Sign_01_16", "Stop_Sign_02_8", "Stop_Sign_108", "Stop_Sign_111", "Stop_Sign_7"], "Fridge": ["Fridge_195", "Fridge_189", "Fridge_Alphabet_01_84", "Fridge_Alphabet_72", "Fridge_60", "Fridge_Alphabet_204", "Fridge_Alphabet_192", "Fridge_01_43"], "1": ["1_8"], "5": ["5_14"], "Birch": ["Birch_35", "Birch_566", "Birch_172", "Birch_175", "Birch_834", "Birch_25", "Birch_24", "Birch_01_160", "Birch_8", "Birch_9", "Birch_4", "Birch_5", "Birch_6", "Birch_7", "Birch_2", "Birch_3", "Birch_36", "Birch_37", "Birch_23", "Birch_21", "Birch_20", "Birch_27", "Birch_26", "Birch_28", "Birch_197", "Birch_16", "Birch_17", "Birch_14", "Birch_15", "Birch_12", "Birch_13", "Birch_10", "Birch_11", "Birch_18", "Birch_19", "Birch_163", "Birch_166", "Birch_169"], "9": ["9_20"], "Shutters": ["Shutters_68", "Shutters_69", "Shutters_62", "Shutters_64", "Shutters_340", "Shutters_354", "Shutters_36", "Shutters_38", "Shutters_79", "Shutters_71", "Shutters_70", "Shutters_75", "Shutters_74", "Shutters_58", "Shutters_50", "Shutters_60", "Shutters_61", "Shutters_66", "Shutters_67", "Shutters_320", "Shutters_59", "Shutters_55", "Shutters_54", "Shutters_57", "Shutters_51", "Shutters_53", "Shutters_52", "Shutters_40", "Shutters_45", "Shutters_48", "Shutters_73", "Shutters_72", "Shutters_77", "Shutters_76", "Shutters_42", "Shutters_44", "Shutters_01_323", "Shutters_49", "Shutters_37", "Shutters_34", "Shutters_33", "Shutters_32", "Shutters_31", "Shutters_30", "Shutters_39", "Shutters_47", "Shutters_313", "Shutters_24", "Shutters_25", "Shutters_26", "Shutters_27", "Shutters_20", "Shutters_21", "Shutters_22", "Shutters_28", "Shutters_29", "Shutters_9", "Shutters_8", "Shutters_5", "Shutters_4", "Shutters_7", "Shutters_6", "Shutters_3", "Shutters_2", "Shutters_120", "Shutters_19", "Shutters_18", "Shutters_11", "Shutters_10", "Shutters_13", "Shutters_12", "Shutters_14", "Shutters_17", "Shutters_16", "Shutters_63", "Shutters_65", "Shutters_43", "Shutters_78", "Shutters_332"], "Structural": ["Structural_Support_01_179"], "Drain": ["Drain_Pipe_02_151", "Drain_Pipe_48", "Drain_Pipe_2", "Drain_Pipe_3", "Drain_Pipe_6", "Drain_Pipe_7", "Drain_Pipe_9", "Drain_Pipe_209", "Drain_Pipe_197", "Drain_Pipe_44", "Drain_Pipe_46", "Drain_Pipe_41", "Drain_Pipe_40", "Drain_Pipe_43", "Drain_Pipe_42", "Drain_Pipe_49", "Drain_Pipe_156", "Drain_Pipe_56", "Drain_Pipe_57", "Drain_Pipe_55", "Drain_Pipe_52", "Drain_Pipe_50", "Drain_Pipe_145", "Drain_Pipe_148", "Drain_Pipe_01_140", "Drain_Pipe_62", "Drain_Pipe_65", "Drain_Pipe_53", "Drain_Pipe_212", "Drain_Pipe_201", "Drain_Pipe_206", "Drain_Pipe_207", "Drain_Pipe_18", "Drain_Pipe_19", "Drain_Pipe_12", "Drain_Pipe_13", "Drain_Pipe_10", "Drain_Pipe_11", "Drain_Pipe_16", "Drain_Pipe_17", "Drain_Pipe_14", "Drain_Pipe_15", "Drain_Pipe_170", "Drain_Pipe_26", "Drain_Pipe_216", "Drain_Pipe_27", "Drain_Pipe_25", "Drain_Pipe_24", "Drain_Pipe_23", "Drain_Pipe_22", "Drain_Pipe_21", "Drain_Pipe_20", "Drain_Pipe_29", "Drain_Pipe_28", "Drain_Pipe_30", "Drain_Pipe_31", "Drain_Pipe_32", "Drain_Pipe_33", "Drain_Pipe_34", "Drain_Pipe_35", "Drain_Pipe_36", "Drain_Pipe_37", "Drain_Pipe_38", "Drain_Pipe_39", "Drain_Pipe_54", "Drain_Pipe_45"], "Flat": ["Flat_Roof_3", "Flat_Roof_4"], "Roof": ["Roof_Edge_Half_Middle_222", "Roof_Corner_558", "Roof_Quart_Corner_4", "Roof_Quart_Corner_2", "Roof_Quart_Corner_3", "Roof_Open_28", "Roof_Open_29", "Roof_Edge_Half_Middle_52", "Roof_Edge_Half_Middle_50", "Roof_Flat_Open_Apex_2", "Roof_Open_77", "Roof_Open_01_198", "Roof_Open_21", "Roof_Edge_End_85", "Roof_Edge_End_182", "Roof_End_Thin_168", "Roof_Middle_Apex_01_7", "Roof_Open_233", "Roof_Open_123", "Roof_Edge_Half_Middle_43", "Roof_Open_85", "Roof_End_Thin_43", "Roof_Edge_End_225", "Roof_Open_209", "Roof_Open_206", "Roof_Open_203", "Roof_Half_407", "Roof_Open_99", "Roof_Middle_Apex_18", "Roof_Middle_Apex_10", "Roof_Middle_Apex_11", "Roof_Middle_Apex_13", "Roof_Middle_Apex_14", "Roof_Middle_Apex_15", "Roof_Middle_Apex_17", "Roof_Edge_End_41", "Roof_Middle_Apex_02_106", "Roof_Middle_Half_2", "Roof_Middle_Half_5", "Roof_Quart_Open_01_555", "Roof_Middle_129", "Roof_Apex_Fill_01_12", "Roof_Open_212", "Roof_End_Thin_27", "Roof_End_Thin_26", "Roof_End_Thin_24", "Roof_End_Thin_28", "Roof_End_256", "Roof_5", "Roof_6", "Roof_Corner_336", "Roof_Edge_Half_Middle_80", "Roof_Corner_199", "Roof_Middle_Apex_20", "Roof_Middle_Apex_23", "Roof_Edge_End_53", "Roof_Edge_End_56", "Roof_Edge_End_57", "Roof_End_Thin_10", "Roof_End_Thin_11", "Roof_Edge_End_3", "Roof_Edge_End_9", "Roof_Edge_End_46", "Roof_Apex_2", "Roof_Apex_9", "Roof_Half_5", "Roof_Half_01_71", "Roof_Edge_End_31", "Roof_Middle_Half_Half_218", "Roof_Open_9", "Roof_Open_3", "Roof_Open_2", "Roof_Apex_332", "Roof_Corner_6", "Roof_Corner_7", "Roof_End_Thin_3", "Roof_End_Thin_01_4", "Roof_End_Thin_8", "Roof_End_Thin_9", "Roof_148", "Roof_Flat_01_474", "Roof_01_122", "Roof_Middle_Apex_19", "Roof_Middle_Apex_8", "Roof_Middle_Apex_9", "Roof_Middle_Apex_2", "Roof_Middle_Apex_3", "Roof_Middle_Apex_6", "Roof_Middle_Apex_7", "Roof_Edge_Half_Middle_76", "Roof_Quart_Corner_01_109", "Roof_Middle_Half_225", "Roof_Edge_Half_Middle_8", "Roof_Edge_Half_Middle_9", "Roof_Edge_Half_Middle_4", "Roof_Edge_Half_Middle_5", "Roof_Edge_Half_Middle_7", "Roof_Edge_Half_Middle_3", "Roof_End_Thin_302", "Roof_Open_148", "Roof_Corner_133", "Roof_Edge_End_16", "Roof_Edge_End_17", "Roof_Edge_End_11", "Roof_Edge_End_13", "Roof_Apex_13", "Roof_Apex_11", "Roof_Apex_10", "Roof_Corner_107", "Roof_Open_16", "Roof_Open_15", "Roof_Open_14", "Roof_Open_13", "Roof_Open_12", "Roof_Open_11", "Roof_Open_8", "Roof_132", "Roof_Edge_Half_Middle_12", "Roof_Corner_236", "Roof_Edge_Half_Middle_19", "Roof_Edge_Half_Middle_21", "Roof_Edge_Half_Middle_20", "Roof_Edge_Half_Middle_27", "Roof_Corner_116", "Roof_Corner_113", "Roof_Edge_Half_Middle_179", "Roof_Edge_End_38", "Roof_End_Thin_239", "Roof_End_Thin_129", "Roof_End_Thin_120", "Roof_End_Thin_122", "Roof_End_Thin_125", "Roof_Middle_Apex_116", "Roof_Quart_Open_277", "Roof_Middle_Half_Half_67", "Roof_Corner_01_56", "Roof_Middle_242", "Roof_Middle_Half_01_143", "Roof_Flat_65", "Roof_Edge_Half_Middle_15", "Roof_Edge_Half_Middle_13", "Roof_Middle_116", "Roof_Middle_Half_Half_4", "Roof_Middle_Half_Half_6", "Roof_Middle_Half_Half_2", "Roof_End_Thin_222", "Roof_End_Thin_139", "Roof_End_Thin_132", "Roof_End_Thin_136", "Roof_Edge_Half_Middle_01_5", "Roof_Middle_Apex_106", "Roof_Half_104", "Roof_End_Thin_109", "Roof_Flat_Open_Apex_01_10", "Roof_Half_113", "Roof_Edge_End_02_14", "Roof_Middle_Half_119", "Roof_Edge_Half_Middle_128", "Roof_End_Thin_110", "Roof_End_Thin_111", "Roof_End_Thin_117", "Roof_End_Thin_119", "Roof_End_Thin_251", "Roof_Quart_Open_138", "Roof_Middle_Half_Half_01_259", "Roof_Edge_End_01_23"], "Cube": ["Cube_178"], "Monument": ["Monument_01_176"], "WorldSettings": ["WorldSettings_1"], "Outdoor": ["Outdoor_Steps_14", "Outdoor_Steps_11", "Outdoor_Steps_12", "Outdoor_Steps_7", "Outdoor_Steps_15", "Outdoor_Steps_13", "Outdoor_Steps_18"], "Street": ["Street_Sign_119", "Street_Sign_116", "Street_Sign_22", "Street_Sign_122", "Street_Sign_01_4", "Street_Sign_19", "Street_Sign_12", "Street_Sign_02_26", "Street_Sign_7", "Street_Sign_29"]}